mlts/__init__.py
mlts/io.py
mlts/normalization.py
mlts/tf/__init__.py
mlts/tf/adapter.py
mlts/tf/generator.py
mlts-0.4.0.dist-info/LICENSE
mlts-0.4.0.dist-info/METADATA
mlts-0.4.0.dist-info/WHEEL
mlts-0.4.0.dist-info/top_level.txt
mlts-0.4.0.dist-info/RECORD
