Metadata-Version: 2.1
Name: mlts
Version: 0.4.0
Summary: Machine Learning Toolset
Home-page: https://github.com/manifest/machine-learning-toolset
Author: Andrei Nesterov
Author-email: ae.nesterov@gmail.com
License: UNKNOWN
Platform: UNKNOWN
Classifier: Development Status :: 2 - Pre-Alpha
Classifier: Intended Audience :: Developers
Classifier: Topic :: Scientific/Engineering :: Artificial Intelligence
Classifier: License :: OSI Approved :: MIT License
Classifier: Programming Language :: Python :: 3
Requires-Python: >=3.6
Requires-Dist: pandas (>=0.25)
Requires-Dist: numpy (>=1.17)
Requires-Dist: tensorflow (>=2.0.0b1)
